ingest_data.py
score.py
train.py
housing_5513-0.1.dist-info/METADATA
housing_5513-0.1.dist-info/WHEEL
housing_5513-0.1.dist-info/entry_points.txt
housing_5513-0.1.dist-info/top_level.txt
housing_5513-0.1.dist-info/RECORD
