Metadata-Version: 2.1
Name: housing_5513
Version: 0.1
Summary: Sample code for coding practice
Author-email: ananya kanagarla <ananya.kanagarla@tigeranalytics.com>
Project-URL: Homepage, https://github.com/ananyaTiger/mle-training/issues/8
Keywords: housing,data training
Classifier: Programming Language :: Python :: 3
Requires-Python: >=3.11
Requires-Dist: numpy
Requires-Dist: pandas
Requires-Dist: scikit-learn
